DataScienceAndAnalyticsForOrdinaryPeople/README.md
DataScienceAndAnalyticsForOrdinaryPeople/__init__.py
DataScienceAndAnalyticsForOrdinaryPeople/__main__.py
DataScienceAndAnalyticsForOrdinaryPeople/file.pdf
DataScienceAndAnalyticsForOrdinaryPeople/index.html
data_science_and_analytics_for_ordinary_people-2024.3.4.0.dist-info/METADATA
data_science_and_analytics_for_ordinary_people-2024.3.4.0.dist-info/WHEEL
data_science_and_analytics_for_ordinary_people-2024.3.4.0.dist-info/entry_points.txt
data_science_and_analytics_for_ordinary_people-2024.3.4.0.dist-info/top_level.txt
data_science_and_analytics_for_ordinary_people-2024.3.4.0.dist-info/RECORD
